numerosPrim/operacion.py
numerosPrim-1.0.dist-info/LICENSE.txt
numerosPrim-1.0.dist-info/METADATA
numerosPrim-1.0.dist-info/WHEEL
numerosPrim-1.0.dist-info/top_level.txt
numerosPrim-1.0.dist-info/RECORD
